hqccnn-0.1.1.dist-info/licenses/LICENSE.txt
lutech_quantum_cnn/__init__.py
lutech_quantum_cnn/cli.py
lutech_quantum_cnn/dataset.py
lutech_quantum_cnn/net.py
lutech_quantum_cnn/operations.py
lutech_quantum_cnn/plot.py
lutech_quantum_cnn/quanvolution.py
lutech_quantum_cnn/quanvolution_new.py
lutech_quantum_cnn/tetris_generator.py
lutech_quantum_cnn/training.py
lutech_quantum_cnn/conf/__init__.py
lutech_quantum_cnn/conf/config.yaml
hqccnn-0.1.1.dist-info/METADATA
hqccnn-0.1.1.dist-info/WHEEL
hqccnn-0.1.1.dist-info/entry_points.txt
hqccnn-0.1.1.dist-info/top_level.txt
hqccnn-0.1.1.dist-info/RECORD
