Metadata-Version: 2.4
Name: hqccnn
Version: 0.1.1
Summary: A quantum convolutional neural network library.
Author-email: Giuseppe <github.crayfish163@passinbox.com>
Maintainer-email: Giuseppe <github.crayfish163@passinbox.com>
License: Attribution 4.0 International
Keywords: quantum computing,neural networks,CNN,machine learning
Classifier: Development Status :: 3 - Alpha
Classifier: Intended Audience :: Developers
Classifier: Intended Audience :: Science/Research
Classifier: Programming Language :: Python :: 3
Classifier: Programming Language :: Python :: 3.8
Classifier: Programming Language :: Python :: 3.9
Classifier: Programming Language :: Python :: 3.10
Classifier: Programming Language :: Python :: 3.11
Classifier: Operating System :: OS Independent
Classifier: Topic :: Scientific/Engineering :: Artificial Intelligence
Classifier: Topic :: Scientific/Engineering :: Physics
Requires-Python: >=3.8
License-File: LICENSE.txt
Requires-Dist: annotated-types==0.7.0
Requires-Dist: antlr4-python3-runtime==4.9.3
Requires-Dist: appdirs==1.4.4
Requires-Dist: asttokens==3.0.0
Requires-Dist: astunparse==1.6.3
Requires-Dist: autograd==1.8.0
Requires-Dist: autoray==0.7.1
Requires-Dist: cachetools==5.5.2
Requires-Dist: certifi==2025.4.26
Requires-Dist: cffi==1.17.1
Requires-Dist: charset-normalizer==3.4.2
Requires-Dist: comm==0.2.2
Requires-Dist: contourpy==1.3.2
Requires-Dist: cryptography==45.0.2
Requires-Dist: cycler==0.12.1
Requires-Dist: debugpy==1.8.14
Requires-Dist: decorator==5.2.1
Requires-Dist: dill==0.4.0
Requires-Dist: executing==2.2.0
Requires-Dist: filelock==3.18.0
Requires-Dist: fonttools==4.58.0
Requires-Dist: fsspec==2025.3.2
Requires-Dist: gast==0.6.0
Requires-Dist: hydra-core==1.3.2
Requires-Dist: ibm-cloud-sdk-core==3.23.0
Requires-Dist: ibm-platform-services==0.65.0
Requires-Dist: idna==3.10
Requires-Dist: ipykernel==6.29.5
Requires-Dist: ipython==9.2.0
Requires-Dist: ipython_pygments_lexers==1.1.1
Requires-Dist: jedi==0.19.2
Requires-Dist: Jinja2==3.1.6
Requires-Dist: joblib==1.5.0
Requires-Dist: jupyter_client==8.6.3
Requires-Dist: jupyter_core==5.7.2
Requires-Dist: kiwisolver==1.4.8
Requires-Dist: MarkupSafe==3.0.2
Requires-Dist: matplotlib==3.10.3
Requires-Dist: matplotlib-inline==0.1.7
Requires-Dist: mpmath==1.3.0
Requires-Dist: nest-asyncio==1.6.0
Requires-Dist: networkx==3.4.2
Requires-Dist: numpy==2.2.5
Requires-Dist: omegaconf==2.3.0
Requires-Dist: packaging==25.0
Requires-Dist: parso==0.8.4
Requires-Dist: pbr==6.1.1
Requires-Dist: PennyLane==0.41.1
Requires-Dist: PennyLane-qiskit
Requires-Dist: PennyLane_Lightning==0.41.1
Requires-Dist: pexpect==4.9.0
Requires-Dist: pillow==11.2.1
Requires-Dist: platformdirs==4.3.8
Requires-Dist: prompt_toolkit==3.0.51
Requires-Dist: psutil==7.0.0
Requires-Dist: ptyprocess==0.7.0
Requires-Dist: pure_eval==0.2.3
Requires-Dist: pycparser==2.22
Requires-Dist: pydantic==2.11.4
Requires-Dist: pydantic_core==2.33.2
Requires-Dist: Pygments==2.19.1
Requires-Dist: PyJWT==2.10.1
Requires-Dist: pyparsing==3.2.3
Requires-Dist: pyspnego==0.11.2
Requires-Dist: python-dateutil==2.9.0.post0
Requires-Dist: PyYAML==6.0.2
Requires-Dist: pyzmq==26.4.0
Requires-Dist: qiskit<2.0.0,>=1.0.0
Requires-Dist: qiskit-aer==0.16.0
Requires-Dist: qiskit-ibm-provider==0.11.0
Requires-Dist: qiskit-ibm-runtime==0.29.0
Requires-Dist: requests==2.32.3
Requires-Dist: requests_ntlm==1.3.0
Requires-Dist: rustworkx==0.16.0
Requires-Dist: scikit-learn==1.6.1
Requires-Dist: scipy==1.15.3
Requires-Dist: scipy-openblas32==0.3.29.0.0
Requires-Dist: setuptools==80.7.1
Requires-Dist: six==1.17.0
Requires-Dist: stack-data==0.6.3
Requires-Dist: stevedore==5.4.1
Requires-Dist: sympy<2.0,==1.13.1
Requires-Dist: termcolor==3.1.0
Requires-Dist: threadpoolctl==3.6.0
Requires-Dist: tomlkit==0.13.2
Requires-Dist: tornado==6.4.2
Requires-Dist: traitlets==5.14.3
Requires-Dist: typing-inspection==0.4.0
Requires-Dist: typing_extensions==4.13.2
Requires-Dist: urllib3==2.4.0
Requires-Dist: wcwidth==0.2.13
Requires-Dist: websocket-client==1.8.0
Requires-Dist: websockets==15.0.1
Requires-Dist: wheel==0.45.1
Dynamic: license-file
